LICENSE.BAYKIT
MANIFEST.in
README.md
bayserver_py
setup.py
bayserver/__init__.py
bayserver.egg-info/PKG-INFO
bayserver.egg-info/SOURCES.txt
bayserver.egg-info/dependency_links.txt
bayserver.egg-info/requires.txt
bayserver.egg-info/top_level.txt
bayserver/conf/cgi_messages.bcf
bayserver/conf/cgi_messages_ja.bcf
bayserver/conf/dockers.bcf
bayserver/conf/h2_messages.bcf
bayserver/conf/h2_messages_ja.bcf
bayserver/conf/h3_messages.bcf
bayserver/conf/httpstatus.bcf
bayserver/conf/messages.bcf
bayserver/conf/messages_h2.bcf
bayserver/conf/messages_h2_ja.bcf
bayserver/conf/messages_ja.bcf
bayserver/conf/messages_servlet.bcf
bayserver/conf/messages_servlet_ja.bcf
bayserver/conf/mimes.bcf
bayserver/conf/quiche_messages.bcf
bayserver/init/cert/oreore.crt
bayserver/init/cert/oreore.jks
bayserver/init/cert/oreore.key
bayserver/init/cert/oreore.p12
bayserver/init/cert/oreore_key.p8
bayserver/init/cert/oreore_key.pem
bayserver/init/plan/bayserver.plan
bayserver/init/plan/groups.plan
bayserver/init/www/cgi-demo/index.html
bayserver/init/www/cgi-demo/info.php
bayserver/init/www/cgi-demo/cgi-bin/test.bat
bayserver/init/www/cgi-demo/cgi-bin/test.cgi
bayserver/init/www/root/bayserver-logo.png
bayserver/init/www/root/favicon.ico
bayserver/init/www/root/index.html
bayserver/init/www/wsgi-demo/file_upload.py
bayserver/init/www/wsgi-demo/file_wrapper.py
bayserver/init/www/wsgi-demo/form_params.py
bayserver/init/www/wsgi-demo/iter_res.py
bayserver/init/www/wsgi-demo/post_form_params.py
bayserver/init/www/wsgi-demo/print_env.py
bayserver/init/www/wsgi-demo/wsgi.py
bayserver/init/www/wsgi-demo/wsgi_demo.py